gptfree/__init__.py
gptfree/core.py
gptfree-0.1.dist-info/METADATA
gptfree-0.1.dist-info/WHEEL
gptfree-0.1.dist-info/top_level.txt
gptfree-0.1.dist-info/RECORD
