Metadata-Version: 2.1
Name: gptfree
Version: 0.1
Summary: A simple wrapper for GPT-free API.
Author: Syo
Author-email: syojp9999@gmail.com
Keywords: GPT API
Requires-Dist: aiohttp >=3.7.4
